<Defs>
	<AlienRace.BackstoryDef>
		<defName>ZoltanBSQuote01</defName>
		<title>Pump up the volume</title>
		<titleShort>DJ</titleShort>
		<baseDescription>NAME loves to drop a good beat or whatever it's called</baseDescription>
		<slot>Adulthood</slot>
		
		<spawnCategories>
		  <li>ZoltanBackstory</li>
		</spawnCategories>
		<skillGains>
			<li><defName>Social</defName><amount>1</amount></li>
			<li><defName>Artistic</defName><amount>2</amount></li>
		</skillGains>
    </AlienRace.BackstoryDef>
	
	<AlienRace.BackstoryDef>
		<defName>ZoltanBSQuote02</defName>
		<title>Private dancer</title>
		<titleShort>ZoltanDancer</titleShort>
		<baseDescription>NAME met her Rockman dancing partner in a marble career. They became famous while she was whirling in the air magnifying her partner powerfull crystals juggling with her fragile body. The spectacle inspired manies and started some kind of transrace golden age.</baseDescription>
		<slot>Adulthood</slot>
		
		<spawnCategories><li>ZoltanBackstory</li></spawnCategories>
		<skillGains>
			<li><defName>Social</defName><amount>1</amount></li>
			<li><defName>Artistic</defName><amount>5</amount></li>
			<li><defName>Construction</defName><amount>-2</amount></li>
			<li><defName>Cooking</defName><amount>-2</amount></li>
			<li><defName>Animals</defName><amount>-2</amount></li>
		</skillGains>
		<forcedTraits>
			<li><defName>Xenophobia</defName><degree>-1</degree><chance>100</chance></li>
		</forcedTraits>

    </AlienRace.BackstoryDef>
</Defs>
<!--
    </AlienRace.BackstoryDef>
		<AlienRace.BackstoryDef>
		<defName>ChildBS</defName>
		<title>/title>
		<titleShort></titleShort>
		<baseDescription></baseDescription>

		<slot>Childhood</slot>
		
		<bodyTypeFemale>Female</bodyTypeFemale>
		<bodyTypeMale>Male</bodyTypeMale>
		<bodyTypeMale>Thin</bodyTypeMale>
		<bodyTypeMale>Fat</bodyTypeMale>
		<bodyTypeMale>Hulk</bodyTypeMale>
		
		<spawnCategories>
			<li>SlugBackstory</li>
		</spawnCategories>
		<skillGains>
			<li><defName>Animals</defName><amount></amount></li>
			<li><defName>Artistic</defName><amount></amount></li>
			<li><defName>Construction</defName><amount></amount></li>
			<li><defName>Cooking</defName><amount></amount></li>
			<li><defName>Crafting</defName><amount></amount></li>
			<li><defName>Growing</defName><amount></amount></li>
			<li><defName>Medicine</defName><amount></amount></li>
			<li><defName>Mining</defName><amount></amount></li>
			<li><defName>Intellectual</defName><amount></amount></li>
			<li><defName>Shooting</defName><amount></amount></li>
			<li><defName>Social</defName><amount></amount></li>
		</skillGains>
		
		<forcedTraits>
			<li><defName>GreenThumb</defName></li>
		</forcedTraits>
		
		<workDisables>
		</workDisables>
    </AlienRace.BackstoryDef>
-->